flask_marrowmailer.py
Flask_MarrowMailer-0.3.0.dist-info/DESCRIPTION.rst
Flask_MarrowMailer-0.3.0.dist-info/METADATA
Flask_MarrowMailer-0.3.0.dist-info/RECORD
Flask_MarrowMailer-0.3.0.dist-info/WHEEL
Flask_MarrowMailer-0.3.0.dist-info/metadata.json
Flask_MarrowMailer-0.3.0.dist-info/top_level.txt
