Metadata-Version: 2.0
Name: Flask-MarrowMailer
Version: 0.3.0
Summary: Marrow Mailer integration for Flask.
Home-page: http://github.com/miguelgrinberg/Flask-MarrowMailer/
Author: Miguel Grinberg
Author-email: miguel.grinberg@gmail.com
License: MIT
Platform: any
Classifier: Environment :: Web Environment
Classifier: Intended Audience :: Developers
Classifier: License :: OSI Approved :: MIT License
Classifier: Operating System :: OS Independent
Classifier: Programming Language :: Python
Classifier: Topic :: Internet :: WWW/HTTP :: Dynamic Content
Classifier: Topic :: Software Development :: Libraries :: Python Modules
Requires-Dist: Flask
Requires-Dist: marrow.mailer
